{
    "id": "80115863",
    "poster": {
        "portrait": "http://art-2.nflximg.net/884a8/b097609ee6fe77781c8375475668f3336ff884a8.jpg",
        "landscape": ""
    },
    "title": "GLOW",
    "year": "2017",
    "synopsis": "In 1980s LA, a crew of misfits reinvent themselves as the Gorgeous Ladies of Wrestling. A comedy by the team behind \"Orange Is the New Black.\"",
    "cast": "Alison Brie, Marc Maron, Jackie Tohn",
    "episodes": [
        {
            "number": 1,
            "title": "Pilot",
            "synopsis": "Desperate to jump-start her career, struggling actress Ruth heads to a casting call at an LA gym -- and quickly realizes it's not a typical audition.",
            "runtime": "37 minutes",
            "link": "http://www.netflix.com/watch/80115864"
        },
        {
            "number": 2,
            "title": "Slouch. Submit.",
            "synopsis": "Cherry tries to whip the final group into shape, while Sam sets out in pursuit of a star for his show. Ruth acts out an uncomfortable scene.",
            "runtime": "32 minutes",
            "link": "http://www.netflix.com/watch/80115865"
        },
        {
            "number": 3,
            "title": "The Wrath of Kuntar",
            "synopsis": "Sam's flashy young producer drops in and whisks the girls off to Malibu to party. But artistic differences soon threaten to spoil the fun.",
            "runtime": "31 minutes",
            "link": "http://www.netflix.com/watch/80115866"
        },
        {
            "number": 4,
            "title": "The Dusty Spur",
            "synopsis": "With just five weeks left to crank out a show, Sam and Bash move all the ladies into a motel. Ruth struggles to nail down a memorable character.",
            "runtime": "32 minutes",
            "link": "http://www.netflix.com/watch/80115867"
        },
        {
            "number": 5,
            "title": "Debbie Does Something",
            "synopsis": "Debbie attends her first wrestling match and has a major epiphany. Meanwhile, Ruth finally finds the inspiration for her alter ego.",
            "runtime": "34 minutes",
            "link": "http://www.netflix.com/watch/80115868"
        },
        {
            "number": 6,
            "title": "This Is One of Those Moments",
            "synopsis": "Sam searches for the perfect \"heel\" to fight Debbie, but she's tough to please. To hone her act, Ruth tags along with Gregory to a family function.",
            "runtime": "29 minutes",
            "link": "http://www.netflix.com/watch/80115869"
        },
        {
            "number": 7,
            "title": "Live Studio Audience",
            "synopsis": "As the women prepare for their first live match, Debbie and Ruth seek outside help with their moves, and Rhonda gives Sam a good-luck gift.",
            "runtime": "35 minutes",
            "link": "http://www.netflix.com/watch/80115870"
        },
        {
            "number": 8,
            "title": "Maybe It’s All the Disco",
            "synopsis": "Jenny whips up a party for Sheila's birthday while Sam helps Ruth deal with a new complication in her personal life. Mark changes his tune with Debbie.",
            "runtime": "31 minutes",
            "link": "http://www.netflix.com/watch/80115871"
        },
        {
            "number": 9,
            "title": "The Liberal Chokehold",
            "synopsis": "With the show's future in jeopardy, Bash and the ladies search for creative ways to drum up cash. A pair of revelations leaves Sam reeling.",
            "runtime": "29 minutes",
            "link": "http://www.netflix.com/watch/80115872"
        },
        {
            "number": 10,
            "title": "Money’s in the Chase",
            "synopsis": "On the day of the big taping, Sam attends to unfinished personal business, while Ruth scrambles to make last-minute changes to the lineup.",
            "runtime": "35 minutes",
            "link": "http://www.netflix.com/watch/80115873"
        }
    ]
}